asimplepypackageformmik/__init__.py
asimplepypackageformmik/_version.py
asimplepypackageformmik/main.py
asimplepypackageformmik-4.0.dist-info/METADATA
asimplepypackageformmik-4.0.dist-info/WHEEL
asimplepypackageformmik-4.0.dist-info/top_level.txt
asimplepypackageformmik-4.0.dist-info/RECORD
