Metadata-Version: 2.1
Name: asimplepypackageformmik
Version: 4.0
Summary: A simple Python package for demonstration purposes
Author-email: Md Mazedul Islam Khan <mazedulislamkhan@gmail.com>
Project-URL: Homepage, https://github.com/mmikhan/asimplepypackageformmik
Project-URL: Bug Tracker, https://github.com/mmikhan/asimplepypackageformmik/issues
Keywords: example,simple
Classifier: Programming Language :: Python :: 3
Classifier: License :: OSI Approved :: MIT License
Classifier: Operating System :: OS Independent
Requires-Python: >=3.6
Provides-Extra: test
Requires-Dist: pytest ; extra == 'test'
